QuanzhanZengchangGongchengshiShizhan/README.md
QuanzhanZengchangGongchengshiShizhan/__init__.py
QuanzhanZengchangGongchengshiShizhan/__main__.py
QuanzhanZengchangGongchengshiShizhan/file.epub
QuanzhanZengchangGongchengshiShizhan/index.html
QuanzhanZengchangGongchengshiShizhan/css/__init__.py
QuanzhanZengchangGongchengshiShizhan/css/annotations.css
QuanzhanZengchangGongchengshiShizhan/css/main.css
QuanzhanZengchangGongchengshiShizhan/css/normalize.css
QuanzhanZengchangGongchengshiShizhan/css/popup.css
QuanzhanZengchangGongchengshiShizhan/font/__init__.py
QuanzhanZengchangGongchengshiShizhan/font/fontello.eot
QuanzhanZengchangGongchengshiShizhan/font/fontello.svg
QuanzhanZengchangGongchengshiShizhan/font/fontello.ttf
QuanzhanZengchangGongchengshiShizhan/font/fontello.woff
QuanzhanZengchangGongchengshiShizhan/img/__init__.py
QuanzhanZengchangGongchengshiShizhan/img/annotator-glyph-sprite.png
QuanzhanZengchangGongchengshiShizhan/img/annotator-icon-sprite.png
QuanzhanZengchangGongchengshiShizhan/img/apple-touch-icon.png
QuanzhanZengchangGongchengshiShizhan/img/cancelfullscreen.png
QuanzhanZengchangGongchengshiShizhan/img/close.png
QuanzhanZengchangGongchengshiShizhan/img/fullscreen.png
QuanzhanZengchangGongchengshiShizhan/img/loader.gif
QuanzhanZengchangGongchengshiShizhan/img/menu-icon.png
QuanzhanZengchangGongchengshiShizhan/img/save.png
QuanzhanZengchangGongchengshiShizhan/img/saved.png
QuanzhanZengchangGongchengshiShizhan/img/settings-s.png
QuanzhanZengchangGongchengshiShizhan/img/settings.png
QuanzhanZengchangGongchengshiShizhan/img/star.png
QuanzhanZengchangGongchengshiShizhan/js/__init__.py
QuanzhanZengchangGongchengshiShizhan/js/epub.js
QuanzhanZengchangGongchengshiShizhan/js/epub.min.js
QuanzhanZengchangGongchengshiShizhan/js/epub.min.map
QuanzhanZengchangGongchengshiShizhan/js/hooks.min.js
QuanzhanZengchangGongchengshiShizhan/js/hooks.min.map
QuanzhanZengchangGongchengshiShizhan/js/reader.js
QuanzhanZengchangGongchengshiShizhan/js/reader.js.map
quanzhan_zengchang_gongchengshi_shizhan-2024.3.1.0.dist-info/METADATA
quanzhan_zengchang_gongchengshi_shizhan-2024.3.1.0.dist-info/WHEEL
quanzhan_zengchang_gongchengshi_shizhan-2024.3.1.0.dist-info/entry_points.txt
quanzhan_zengchang_gongchengshi_shizhan-2024.3.1.0.dist-info/top_level.txt
quanzhan_zengchang_gongchengshi_shizhan-2024.3.1.0.dist-info/RECORD
